LICENSE
MANIFEST.in
README.rst
setup.py
time_benchmark/__init__.py
time_benchmark/time_benchmark.py
time_benchmark.egg-info/PKG-INFO
time_benchmark.egg-info/SOURCES.txt
time_benchmark.egg-info/dependency_links.txt
time_benchmark.egg-info/top_level.txt