Metadata-Version: 1.1
Name: time-benchmark
Version: 0.1.1
Summary: Time Benchmark
Home-page: https://github.com/pnpnpn/time-benchmark-py
Author: Patrick Ng
Author-email: pn.appdev@gmail.com
License: UNKNOWN
Platform: UNKNOWN
Classifier: Development Status :: 4 - Beta
Classifier: Intended Audience :: Developers
Classifier: License :: OSI Approved :: MIT License
Classifier: Natural Language :: English
Classifier: Operating System :: OS Independent
Classifier: Programming Language :: Python
Classifier: Topic :: Software Development :: Libraries :: Python Modules
